{
    "camera_model": "PINHOLE",
    "fx": 698.21,
    "fy": 698.58,
    "cx": 500.56,
    "cy": 396.42,
    "W": 1024,
    "H": 768,
    "k1": -0.34512,
    "k2": 0.17894920,
    "k3": -0.000453977,
    "p1": 1.282142e-5,
    "p2": -0.05901579,
    "image_crops": [0, 0, 0, 0],
    "system": "modal",
    "static_transforms_file": "./static_transforms/modal.json",
    "camera_frame_names": ["pose_to_camera"],
    "image_topic": ["/republished_image"],
    "pose_topic": "/republished_pose",
    "depth_topic": ["/republished_pointcloud"],
    "depth_scale_factor": 1.0,
    "depth_max": 5.0,
    "depth_min": 0.1,
    "compressed_rgb": false,
    "undistort_rgb": true,
    "pose_reject_radius": 0.1,
    "center_to_first_pose": true,
    "topic_sync": "approximate",
    "topic_slop": 0.1,
    "data_update_freq": 3.0,
    "eval_save_freq": 1.0,
    "scene_scale_factor": 1.0,
    "semantics_field_scale": 1.0,
    "semantics_positives": ["chair"],
    "semantics_negatives": ["stuff"]
}
